{
  "SKU": "DS-PY-001",
  "interpreter": 1,
  "type": "GAP",
  "language": "Python",
  "knowledgeArea": "Data Science",
  "category": "Lógica de Programação",
  "subCategory": "Operadores Lógicos",
  "level": "Basic",
  "tagsOrConcepts": [
    "operadores lógicos"
  ],
  "text": [
    "Um analista de dados precisa isolar de sua base apenas os registros que representem idosos ou menores de idade. Sendo x a idade do cliente cadastrado, qual operador lógico a seguir melhor completa a lacuna para atender esta demanda?",
    "x >= 60 {{GAP}} x < 18"
  ],
  "alternatives": [
    {
      "value": "and",
      "hint": "",
      "id": "1ee3543b-02b9-6042-2ab6-a5f5785f1af5"
    },
    {
      "value": "or",
      "hint": "",
      "id": "1ee3543b-02b9-6043-5007-e3744557c7af"
    },
    {
      "value": "not",
      "hint": "",
      "id": "1ee3543b-02b9-6044-e742-f391183cac5e"
    }
  ],
  "gaps": [
    {
      "expected": "or",
      "feedbacks": [
        {
          "value": "and",
          "text": "Para implementar a lógica correta, precisamos usar o operador `or`"
        },
        {
          "value": "not",
          "text": "Para implementar a lógica correta, precisamos usar o operador `or`"
        }
      ]
    }
  ],
  "id": "1ee3543b-02b9-6041-0919-3cc165c948d0"
}